dselib/__init__.py
dselib/analysis.py
dselib/datamodel.py
dselib/fileio.py
dselib/pipeline.py
ipylib2/__init__.py
ipylib2/ifile.py
realestate/__init__.py
realestate/dataengine.py
dselib-0.1.3.dist-info/LICENSE
dselib-0.1.3.dist-info/METADATA
dselib-0.1.3.dist-info/WHEEL
dselib-0.1.3.dist-info/top_level.txt
dselib-0.1.3.dist-info/RECORD
