Metadata-Version: 2.1
Name: dselib
Version: 0.1.3
Summary: NETVIBES / Data Science Experience
Home-page: https://github.com/innovata/DataScienceExperience
Author: innovata
Author-email: iinnovata@gmail.com
Classifier: Programming Language :: Python :: 3
Classifier: License :: OSI Approved :: MIT License
Classifier: Operating System :: OS Independent
Requires-Python: >=3.8
License-File: LICENSE
